nidb_to_bids/__init__.py
nidb_to_bids/parse_nidb_metadata.py
nidb_to_bids-0.0.2.dist-info/LICENSE
nidb_to_bids-0.0.2.dist-info/METADATA
nidb_to_bids-0.0.2.dist-info/WHEEL
nidb_to_bids-0.0.2.dist-info/entry_points.txt
nidb_to_bids-0.0.2.dist-info/top_level.txt
nidb_to_bids-0.0.2.dist-info/RECORD
