Metadata-Version: 2.1
Name: nidb-to-bids
Version: 0.0.2
Summary: Our lab's code to convert data dumped from NiDB to BIDS
Home-page: https://github.com/nimh-mbdu/nidb_to_bids
Author: Dylan Nielson
Author-email: Dylan.Nielson@gmail.com
License: UNKNOWN
Platform: UNKNOWN
Classifier: Programming Language :: Python :: 3
Classifier: License :: CC0 1.0 Universal (CC0 1.0) Public Domain Dedication
Classifier: Operating System :: POSIX
Requires-Dist: pandas
Requires-Dist: numpy
Requires-Dist: nibabel
Requires-Dist: Click
Requires-Dist: joblib
